{
    "__DOCUMENTATION__": {
        "sorry": "json has no native documentation formatting. This will do",
        "locales": "https://discord.com/developers/docs/dispatch/field-values#predefined-field-values-accepted-locales",
        "formatting": {
            "keeping tidy": "please prefix command specific strings with COMMANDNAME_ as this getting collisions.",
            "grouping": "please keep any general strings (not bound to a specific command) at the top",
            "inline variables": "you can include variables by enclosing their name in {NAME}. You can see which variables are availible for which command by checking where the label is used"
        }
    },


    "done" : {
        "en-GB": "done",
        "sv-SE": "klart"
    },
    "issue": {
        "en-GB": "issue",
        "sv-SE": "problem"
    },
    "command_broke": {
        "en-GB": "something went wrong and it probably wasnt your fault",
        "sv-SE": "n친got gick paj och det var inte ditt fel"
    },
    "needs_manage_threads": {
        "en-GB": "bot needs `MANAGE_THREADS` for this command",
        "sv-SE": "botten beh칬ver `MANAGE_THREADS` f칬r detta kommando"
    },
    "user_needs_manage_threads": {
        "en-GB": "you need `MANAGE_THREADS` to use it.",
        "sv-SE": "du beh칬ver `MANAGE_THREADS` f칬r att anv칛nda det."
    },
    "no_perms_for_command": {
        "en-GB": "You do not have permission to use /{command} command.",
        "sv-SE": "Du har inte till친telse att anv칛nda /${command} kommandot."
    },
    "bot_by": {
        "en-GB": "Bot by Family friendly#6191",
        "sv-SE": "Bot skapad av Family friendly#6191"
    },
    "watch_on": {
        "en-GB": "bot **will make sure** <#{id}> is un-archived",
        "sv-SE": "botten kommer se till att <#{id}> 칛r o-arkiverad"
    },
    "watch_off": {
        "en-GB": "bot **will no longer keep** <#{id}> un-archived",
        "sv-SE": "botten kommer ej l칛ngre h친lla <#{id}> o-arkiverad"
    },
    "watch_issue_add": {
        "en-GB": "bot failed to add thread to watchlist. Sorry about that",
        "sv-SE": "botten misslyckades att l칛gga till tr친den till listan. Ber om urs칛kt"
    },
    "watch_issue_remove": {
        "en-GB": "bot failed to remove thread from database. Sorry about that",
        "sv-SE": "botten misslyckades att ta bort tr친den fr친n listan. Ber om urs칛kt"
    },
    "threads_is_watching": {
        "en-GB": "thread-watcher is watching {amount} thread(s) in this server!",
        "sv-SE": "thread-watcher h친ller koll p친 {amount} tr친d(ar) i denna server!"
    },
    "threads_none_watched": {
        "en-GB": "no threads are being watched!",
        "sv-SE": "inga tr친dar h친lls o-arkiverade!"
    },
    "batch_forbidden_characters": {
        "en-GB": "your pattern \"{pattern}\" includes forbidden characters",
        "sv-SE": "ditt text-m칬nster \"{pattern}\" inneh친ller f칬rbjudna tecken"
    },
    "batch_result": {
        "en-GB": "游릭 {succeeded} succeeded. 游댮 {failed} failed",
        "sv-SE": "游릭 {succeeded} lyckades. 游댮 {failed} misslyckades"
    }
}
